{
  "key": "opensourceways--issue_state_monitor",
  "last_delta": "2026-06-29T00:58:45Z",
  "last_refresh": "2026-06-30T01:06:39Z",
  "digest_count": 0,
  "status": "dormant",
  "repo": {
    "cloned": false,
    "clone_url": null,
    "last_commit": "e00f692d",
    "last_indexed": "2026-06-28T05:16:22Z"
  },
  "quick_stats": {
    "files": 8,
    "primary_lang": "Go",
    "size_kb": 278
  },
  "_has_digest": false,
  "_has_codebase": false,
  "category": "observability",
  "tags": [
    "data",
    "go",
    "observability",
    "\u56e2\u961f\u4e3b\u5bfc"
  ],
  "language": "Go",
  "codebase_stats": {
    "nodes": 50,
    "edges": 102
  }
}