{
  "key": "opensourceways--helm-charts",
  "last_delta": "2026-06-29T00:51:50Z",
  "last_refresh": "2026-06-28T05:26:31Z",
  "digest_count": 1,
  "status": "active",
  "repo": {
    "cloned": false,
    "clone_url": null,
    "last_commit": "4dd4535b",
    "last_indexed": "2026-06-28T05:16:22Z"
  },
  "quick_stats": {
    "files": 684,
    "primary_lang": "YAML",
    "size_kb": 3064
  },
  "codebase_stats": {
    "nodes": 2674,
    "edges": 2803
  },
  "_has_digest": true,
  "_has_codebase": true
}