{
  "key": "opensourceways--app-cla-signing",
  "last_delta": "2026-06-29T00:58:45Z",
  "last_refresh": "2026-06-28T05:13:14Z",
  "digest_count": 0,
  "status": "dormant",
  "repo": {
    "cloned": false,
    "clone_url": null,
    "last_commit": "48329710",
    "last_indexed": "2026-06-28T05:13:14Z"
  },
  "codebase_stats": {
    "nodes": 728,
    "edges": 1998
  },
  "_has_digest": false,
  "_has_codebase": true,
  "category": "backend",
  "tags": [
    "auth",
    "go",
    "\u56e2\u961f\u4e3b\u5bfc"
  ],
  "language": "Go"
}