{
  "key": "opensourceways--argus-worker",
  "last_delta": "2026-06-29T00:58:45Z",
  "last_refresh": "2026-06-30T01:56:44Z",
  "digest_count": 0,
  "status": "dormant",
  "repo": {
    "cloned": false,
    "clone_url": null,
    "last_commit": "d7451c25",
    "last_indexed": "2026-06-28T05:14:18Z"
  },
  "codebase_stats": {
    "nodes": 203,
    "edges": 309
  },
  "_has_digest": false,
  "_has_codebase": true,
  "category": "tool",
  "tags": [
    "ci-cd",
    "git-platform",
    "go",
    "kubernetes",
    "workflow",
    "\u56e2\u961f\u4e3b\u5bfc"
  ],
  "language": "Go"
}